<?xml version="1.0" encoding="utf-8"?>
<map>
  <node name="Customer" refs="3" depth="0" schema="dbo" label="Customer" schemaLabel="Dbo">
    <node name="Users" refs="1" depth="1" schema="dbo" label="Users" schemaLabel="Dbo">
      <node name="UserRoles" refs="0" depth="2" schema="dbo" label="User Roles" schemaLabel="Dbo" />
    </node>
    <node name="ConsignmentStockDashboard" refs="0" depth="1" schema="dbo" label="Consignment Stock Dashboard" schemaLabel="Dbo" />
    <node name="ConsignmentUsageDashboard" refs="0" depth="1" schema="dbo" label="Consignment Usage Dashboard" schemaLabel="Dbo" />
  </node>
  <node name="Product" refs="2" depth="0" schema="dbo" label="Product" schemaLabel="Dbo">
    <node name="ConsignmentStock" refs="0" depth="1" schema="dbo" label="Consignment Stock" schemaLabel="Dbo" />
    <node name="ConsignmentUsage" refs="0" depth="1" schema="dbo" label="Consignment Usage" schemaLabel="Dbo" />
  </node>
  <node name="Roles" refs="1" depth="0" schema="dbo" label="Roles" schemaLabel="Dbo" />
  <node name="Company" refs="1" depth="0" schema="dbo" label="Company" schemaLabel="Dbo" />
  <node name="ConsignmentPurchaseOrder" refs="1" depth="0" schema="dbo" label="Consignment Purchase Order" schemaLabel="Dbo" />
  <node name="DocumentType" refs="1" depth="0" schema="dbo" label="Document Type" schemaLabel="Dbo">
    <node name="Document" refs="0" depth="1" schema="dbo" label="Document" schemaLabel="Dbo" />
  </node>
</map>